Project/traffic_light/traffic_light_controller.v
module traffic_light_controller(TA, TB, clk, rst, RA, YA, GA, RB, YB, GB)
	input TA, TB, clk, rst;
	typedef enum logic [1:0] {S0, S1, S2, S3} s;
	S [1:0] state, nextstate;
	output RA, YA, GA, RB, YB, GB;
	always @(posedge clk, posedge rst)
		if(rst) state <= S0;
		else state <= nextstate;
	always
		case(state)
			S0: if(TA) nextstate <= S0;
			    else nextstate <= S1;
			S1: nextstate <= S2;
			S2: if(TB) nextstate <= S2;
			    else nextstate <= S3;
			S3: nextstate <= S0;
			default: nextstate <= S0;
		endcase
	assign RA = (state == S2 | state == S3);
	assign YA = (state == S1);
	assign GA = (state == S0);
	assign RB = (state == S0 | state == S1);
	assign YB = (state == S3);
	assign GB = (state == S2);
endmodule

module LFSR(clk, rst, T)
	input clk, rst;
	output reg T, [4:0]  Q;
	wire feedback;
	assign feedback = ~(Q[2] ^ Q[4]);
	always @(posedge clk, posedge rst)
		begin
			if(rst)
				begin
					Q = 5'b0;
					T = 1'b0;
				end
			else
				begin
					Q = {Q[3], feedback}
					T = Q[1];
				end
		end
endmodule

Project/traffic_light/traffic_light_controller_tb.v
module test_TLC();
	input TA, TB, clk, rst;
	output RA, YA, GA, RB, YB, GB;
	LFSR lfsr(clk, rst, T);
	traffic_light_controller DUT(TA, TB, clk, rst, RA, YA, GA, RB, YB, GB);
	always
		begin
			clk = 1;
			#5;
			clk = 0;
			#5;
		end
	initial
		begin
			rst = 1;
			#10;
			rst = 0;
		end
	initial
		begin
			$dumpfile ("testtlc.vcd");
			$dumpvars (0, DUT);
			for(i=0; i<20; i+=1)
			begin
				TA = lfsr.Q[0];
				TB = lfsr.Q[1];
				#10;
				$display ("TA = %b, TB = %b, RA = %b, YA = %b, GA = %b, RB = %b, YB = %b, GB = %b", TA, TB, RA, YA, GA, RB, YB, GB);
			end
			$finish
		end
endmodule

Project/traffic_light/testtlc.vcd
$date
	Tue May  8 21:55:38 2018
$end
$version
	Icarus Verilog
$end
$timescale
	1ps
$end
$scope module test_TLC $end
$scope module DUT $end
$var wire 1 ! RA $end
$var wire 1 " RB $end
$var wire 1 # TA $end
$var wire 1 $ TB $end
$var wire 1 % clk $end
$var wire 1 & rst $end
$var wire 1 ' YB $end
$var wire 1 ( YA $end
$var wire 1 ) GB $end
$var wire 1 * GA $end
$var reg 2 + nextstate [1:0] $end
$var reg 2 , state [1:0] $end
$upscope $end
$upscope $end
$enddefinitions $end
#0
$dumpvars
b0 ,
b1 +
1*
0)
0(
0'
1&
1%
x$
x#
1"
0!
$end
#5000
0%
#10000
b10 +
0*
1(
b1 ,
1%
0$
0#
0&
#15000
0%
#20000
b11 +
1!
0"
0(
1)
b10 ,
1%
1#
#25000
0%
#30000
b10 +
1%
1$
#35000
0%
#40000
1%
#45000
0%
#50000
1%
0#
#55000
0%
#60000
0)
1'
b11 ,
b0 +
1%
0$
#65000
0%
#70000
0!
1"
1*
0'
b0 ,
1%
1#
#75000
0%
#80000
0*
1(
b1 ,
b10 +
1%
1$
0#
#85000
0%
#90000
b11 +
1!
0"
0(
1)
b10 ,
1%
0$
#95000
0%
#100000
b0 +
0)
1'
b11 ,
1%
#105000
0%
#110000
0!
1"
1*
0'
b0 ,
1%
1#
#115000
0%
#120000
0*
1(
b1 ,
b10 +
1%
1$
0#
#125000
0%
#130000
b11 +
1!
0"
0(
1)
b10 ,
1%
0$
1#
#135000
0%
#140000
b10 +
1%
1$
0#
#145000
0%
#150000
0)
1'
b11 ,
b0 +
1%
0$
1#
#155000
0%
#160000
0!
1"
1*
0'
b0 ,
1%
1$
#165000
0%
#170000
1%
#175000
0%
#180000
1%
#185000
0%
#190000
0*
1(
b1 ,
b10 +
1%
0#
#195000
0%
#200000
1!
0"
0(
1)
b10 ,
1%
